CHANGELOG.md
LICENSE.txt
README.md
UPGRADING.txt
flickrapi/__init__.py
flickrapi/auth.py
flickrapi/cache.py
flickrapi/call_builder.py
flickrapi/core.py
flickrapi/exceptions.py
flickrapi/html.py
flickrapi/shorturl.py
flickrapi/sockutil.py
flickrapi/tokencache.py
flickrapi/xmlnode.py
flickrapi-2.3.1.dist-info/DESCRIPTION.rst
flickrapi-2.3.1.dist-info/METADATA
flickrapi-2.3.1.dist-info/RECORD
flickrapi-2.3.1.dist-info/WHEEL
flickrapi-2.3.1.dist-info/metadata.json
flickrapi-2.3.1.dist-info/top_level.txt
flickrapi-2.3.1.dist-info/zip-safe
